[
  {
    "full_name": "balena-io/balena-cli",
    "stargazers_count": 288,
    "open_issues_count": 299,
    "forks_count": 85
  },
  {
    "full_name": "open-sauced/open-sauced",
    "stargazers_count": 315,
    "open_issues_count": 29,
    "forks_count": 90
  },
  {
    "full_name": "fomantic/Fomantic-UI",
    "stargazers_count": 2265,
    "open_issues_count": 219,
    "forks_count": 223
  },
  {
    "full_name": "blueluna/psila",
    "stargazers_count": 6,
    "open_issues_count": 1,
    "forks_count": 3
  },
  {
    "full_name": "esp-rs/docs",
    "stargazers_count": 3,
    "open_issues_count": 1,
    "forks_count": 0
  }
]